WebtoonScraper/__init__.py
WebtoonScraper/__main__.py
WebtoonScraper/base.py
WebtoonScraper/directory_state.py
WebtoonScraper/exceptions.py
WebtoonScraper/py.typed
WebtoonScraper/scrapers/__init__.py
WebtoonScraper/scrapers/_callback_manager.py
WebtoonScraper/scrapers/_helpers.py
WebtoonScraper/scrapers/_naver_webtoon.py
WebtoonScraper/scrapers/_scraper.py
WebtoonScraper/scrapers/py.typed
webtoonscraper-5.10.3.dist-info/METADATA
webtoonscraper-5.10.3.dist-info/WHEEL
webtoonscraper-5.10.3.dist-info/entry_points.txt
webtoonscraper-5.10.3.dist-info/licenses/LICENSE
webtoonscraper-5.10.3.dist-info/RECORD
