Metadata-Version: 2.4
Name: WebtoonScraper
Version: 5.10.3
Summary: Scraping webtoons with ease
Project-URL: Documentation, https://webtoonscraper.readthedocs.io/ko/latest/
Project-URL: Repository, https://github.com/ilotoki0804/WebtoonScraper
Project-URL: Changelog, https://webtoonscraper.readthedocs.io/ko/latest/releases/
Project-URL: Funding, https://www.patreon.com/ilotoki0804
Author-email: ilotoki0804 <ilotoki0804@gmail.com>
License-Expression: Apache-2.0
License-File: LICENSE
Keywords: download webtoon,naver webtoon,webtoon,webtoon downloader,webtoon scraper
Classifier: License :: OSI Approved :: Apache Software License
Classifier: Operating System :: OS Independent
Classifier: Programming Language :: Python :: 3
Classifier: Programming Language :: Python :: 3.11
Classifier: Programming Language :: Python :: 3.12
Classifier: Programming Language :: Python :: 3.13
Requires-Python: >=3.11
Requires-Dist: fieldenum~=0.2.0
Requires-Dist: filetype>=1.2.0
Requires-Dist: httpc~=0.13.0
Requires-Dist: pillow>=10.4.0
Requires-Dist: pyfilename~=0.6.0
Requires-Dist: rich>=13.8.0
Requires-Dist: yarl>=1.9.11
Provides-Extra: full
